pyramid_jinja2_webpack-0.1.1.dist-info/METADATA
pyramid_jinja2_webpack-0.1.1.dist-info/WHEEL
pyramid_jinja2_webpack-0.1.1.dist-info/DESCRIPTION.rst
pyramid_jinja2_webpack-0.1.1.dist-info/metadata.json
pyramid_jinja2_webpack-0.1.1.dist-info/RECORD
pyramid_jinja2_webpack-0.1.1.dist-info/top_level.txt
pyramid_jinja2_webpack/__init__.py
